pysatModels/__init__.py
pysatModels/version.txt
pysatModels/models/__init__.py
pysatModels/models/pydineof_dineof.py
pysatModels/models/sami2py_sami2.py
pysatModels/models/ucar_tiegcm.py
pysatModels/models/methods/__init__.py
pysatModels/models/methods/general.py
pysatModels/tests/__init__.py
pysatModels/tests/test_methods_general.py
pysatModels/tests/test_models.py
pysatModels/tests/test_utils_compare.py
pysatModels/tests/test_utils_convert.py
pysatModels/tests/test_utils_extract.py
pysatModels/tests/test_utils_match.py
pysatModels/tests/test_utils_testing.py
pysatModels/tests/test_data/dineof_2009-01-01.nc
pysatModels/utils/__init__.py
pysatModels/utils/compare.py
pysatModels/utils/convert.py
pysatModels/utils/extract.py
pysatModels/utils/match.py
pysatModels/utils/testing.py
pysatModels-0.1.0.dist-info/LICENSE
pysatModels-0.1.0.dist-info/METADATA
pysatModels-0.1.0.dist-info/WHEEL
pysatModels-0.1.0.dist-info/top_level.txt
pysatModels-0.1.0.dist-info/RECORD
