Metadata-Version: 2.1
Name: pysatModels
Version: 0.1.0
Summary: 'Supports model analysis and model-data comparisons'
Home-page: https://github.com/pysat/pysatModels
Author: Pysat Development Team
Author-email: pysat.developers@gmail.com
License: UNKNOWN
Platform: UNKNOWN
Classifier: Development Status :: 3 - Alpha
Classifier: Topic :: Scientific/Engineering :: Physics
Classifier: Intended Audience :: Science/Research
Classifier: License :: Freely Distributable
Classifier: Natural Language :: English
Classifier: Programming Language :: Python :: 3
Classifier: Programming Language :: Python :: 3.8
Classifier: Programming Language :: Python :: 3.9
Classifier: Programming Language :: Python :: 3.10
Classifier: Operating System :: MacOS :: MacOS X
Classifier: Operating System :: POSIX :: Linux
Classifier: Operating System :: Microsoft :: Windows
Requires-Python: >=3.5
License-File: LICENSE
Requires-Dist: numpy
Requires-Dist: packaging
Requires-Dist: pandas
Requires-Dist: pyForecastTools
Requires-Dist: pysat
Requires-Dist: scipy
Requires-Dist: xarray
